viennaptm/__init__.py
viennaptm-0.0.1.dist-info/LICENSE
viennaptm-0.0.1.dist-info/METADATA
viennaptm-0.0.1.dist-info/WHEEL
viennaptm-0.0.1.dist-info/top_level.txt
viennaptm-0.0.1.dist-info/RECORD
