Metadata-Version: 2.1
Name: viennaptm
Version: 0.0.1
Summary: Python package to add post-translational modifications to protein structures
Home-page: http://vienna-ptm.univie.ac.at
Author: Christian Margreitter, Sophie Margreitter, Bojan Zagrovic
Author-email: christian.margreitter@gmail.com
License: UNKNOWN
Platform: UNKNOWN
Classifier: Programming Language :: Python :: 3
Classifier: License :: OSI Approved :: MIT License
Classifier: Operating System :: OS Independent
